Metadata-Version: 2.1
Name: common-prstub
Version: 0.0.0a1
Summary: Reserved package name
Home-page: https://github.com/KyleKing/not-on-pypi
Author: Kyle King
Author-email: dev.act.kyle@gmail.com
License: Unlicense
Platform: UNKNOWN
Classifier: License :: Public Domain
